spatialsignificance.cpython-38-x86_64-linux-gnu.so
spatialsignificance-0.0.1.dist-info/RECORD
spatialsignificance-0.0.1.dist-info/WHEEL
spatialsignificance-0.0.1.dist-info/METADATA
spatialsignificance-0.0.1.dist-info/LICENSE.txt
spatialsignificance-0.0.1.dist-info/top_level.txt
