Metadata-Version: 2.1
Name: spatialsignificance
Version: 0.0.1
Summary: Resampling spatial data under constraints
Home-page: https://github.com/rudyarthur/spatialsignificance
Author: Rudy Arthur
Author-email: rudy.d.arthur@gmail.com
License: GNU GENERAL PUBLIC LICENSE Version 3
Project-URL: Documentation, https://github.com/rudyarthur/spatialsignificance
Project-URL: Code, https://github.com/rudyarthur/spatialsignificance
Project-URL: Issue tracker, https://github.com/rudyarthur/spatialsignificance/issues
Platform: UNKNOWN
Classifier: Development Status :: 1 - Planning
Classifier: License :: OSI Approved :: GNU General Public License v3 (GPLv3)
Classifier: Intended Audience :: Education
Classifier: Intended Audience :: Science/Research
Classifier: Topic :: Scientific/Engineering
Classifier: Topic :: Scientific/Engineering :: Mathematics
Classifier: Natural Language :: English
Classifier: Operating System :: OS Independent
Classifier: Programming Language :: C
Classifier: Programming Language :: Cython
Classifier: Programming Language :: Python
Classifier: Programming Language :: Python :: 3
Classifier: Programming Language :: Python :: 3.4
Classifier: Programming Language :: Python :: 3.5
Classifier: Programming Language :: Python :: 3.6
Classifier: Programming Language :: Python :: 3.7
Classifier: Programming Language :: Python :: 3 :: Only
Classifier: Programming Language :: Python :: Implementation :: CPython
Requires-Python: >=3.8
